[
    {
        "id": "d5219c1d-a258-4d8d-8d26-d1b17ae8f9a6",
        "title": "애니를 뚫고 나와버린 고인물들의 \"귀멸의 칼날\" 게임 속 다키..ㄷ",
        "description": "오늘은 귀멸의 칼날 2기 환락의 거리편 특집으로 준비해보았습니다!!\n\n오늘 영상만큼은 고정댓글 정말 중요합니다 영상 끝까지 시청해주세요!!\n\n썸네일 - 유진씨\n\n👺타임라인👺\n00:00 인트로\n00:41 다키 털어보기\n03:31 구독자 필수정보\n06:06 오늘의 결론\n\n문의/광고/협찬 ask.endevor@gmail.com 편하게 연락주세요!\n\n#귀멸의칼날 #히노카미혈풍담 #귀멸의칼날게임\n#귀멸의칼날3기 #대장장이마을편 #환락의거리편 \n#귀멸의칼날무한열차 #귀멸2기",
        "thumbnail": "https://i.ytimg.com/vi/aJlHvZ6CeM8/mqdefault.jpg",
        "youtubeVideoId": "aJlHvZ6CeM8",
        "uploadedDate": "2022-10-20T07:01:20Z",
        "viewCount": 6134,
        "isCommercial": "False"
    }
]